{"key":"content:index.md","generatedAt":"2021-10-13T13:08:12.797Z","mtime":"2021-10-13T13:08:12.772Z","slug":"","title":"The Hybrid Vue Framework","position":"999900000000","to":"/","draft":false,"page":true,"language":"en","navigation":false,"template":"Page","description":"使用 Vue 3 构建您的下一个应用程序，体验混合渲染、强大的数据获取和新功能。Nuxt 3 是一个开源框架，使 Web 开发变得简单而强大。","empty":false,"body":{"raw":"---\nnavigation: false\ntemplate: Page\ntitle: The Hybrid Vue Framework\ndescription: '使用 Vue 3 构建您的下一个应用程序，体验混合渲染、强大的数据获取和新功能。Nuxt 3 是一个开源框架，使 Web 开发变得简单而强大。'\n---\n\n::HomeHero\n---\nprimary:\n  text: Star on GitHub\n  url: https://github.com/nuxt/framework\n  icon: IconGitHub\n---\n\n#title\nThe Hybrid [Vue]{.text-primary} Framework\n\n#description\n使用 Vue 3 构建您的下一个应用程序，体验混合式渲染、强大的数据获取和新功能。Nuxt 3 是一个开源框架，使 Web 开发变得简单而强大。\n\n#secondary-button\n:button-link[开始]{ href=\"/getting-started\" size=\"medium\" aria-label=\"Get started\" }\n::\n\n::home-features{.dark:bg-secondary-darkest .bg-gray-50}\n---\ncategory: 发现\n---\n#title\n新功能\n\n#description\nNuxt 3 已重新架构，内核更小，并针对更快的性能和更好的开发人员体验进行了优化。\n\n#default\n  ::section-content-item\n  ---\n  title: Lighter\n  description: Up to 75x smaller server deployments and smaller client bundle targeting modern browsers.\n  image: IconFeather\n  imageClass: w-10 h-10\n  ---\n  ::\n  ::section-content-item\n  ---\n  title: Faster\n  description: '优化的冷启动与动态服务器代码拆分，由 nitro 提供支持.'\n  image: IconRabbit\n  imageClass: w-10 h-10\n  ---\n  ::\n  ::section-content-item\n  ---\n  soon: true\n  title: Hybrid\n  description: 'Incremental Static Generation and other advanced modes are now possible.'\n  image: IconHybrid\n  imageClass: w-10 h-10\n  ---\n  ::\n  ::section-content-item\n  ---\n  title: Suspense\n  description: 'Fetch data in any component, before or after navigation.'\n  image: IconSuspense\n  imageClass: w-10 h-10\n  ---\n  ::\n  ::section-content-item\n  ---\n  title: Composition API\n  description: \"使用 Composition API 和 Nuxt 3 的可组合物实现真正的代码可重用性。\"\n  image: IconCAPI\n  imageClass: w-10 h-10\n  ---\n  ::\n  ::section-content-item\n  ---\n  title: Nuxt CLI\n  description: '全新的零依赖体验，可轻松搭建脚手架和模块集成。'\n  image: IconCLI\n  imageClass: w-10 h-10\n  ---\n  ::\n  ::section-content-item\n  ---\n  soon: true\n  title: Nuxt Devtools\n  description: 'Work faster with info and quick fixes right in the browser.'\n  image: IconDevtools\n  imageClass: w-10 h-10\n  ---\n  ::\n  ::section-content-item\n  ---\n  title: Nuxt Kit\n  description: 'Brand new module development with Typescript and cross-version compatibility.'\n  image: IconKit\n  imageClass: w-10 h-10\n  ---\n  ::\n  ::section-content-item\n  ---\n  title: Webpack 5\n  description: 'Faster build time and smaller bundle size, with no configuration required.'\n  image: IconWebpack\n  imageClass: w-10 h-10\n  ---\n  ::\n  ::section-content-item\n  ---\n  title: Vite\n  description: 'Vue 3 是您下一个 Web 应用程序的坚实基础。'\n  image: IconVite\n  imageClass: w-10 h-10\n  ---\n  ::\n  ::section-content-item\n  ---\n  title: Vue 3\n  description: 'Vue 3 is a solid foundation for your next web app.'\n  image: IconVue\n  imageClass: w-10 h-10\n  ---\n  ::\n  ::section-content-item\n  ---\n  title: TypeScript\n  description: 'Built with native TypeScript and ESM - no extra steps required.'\n  image: IconTypeScript\n  imageClass: w-10 h-10\n  ---\n  ::\n#bottom\n  :button-link[开始]{ href=\"/getting-started\" size=\"medium\" aria-label=\"Get started\" }\n::\n\n::section{.py-20 .text-lg}\n  ::nuxt-container{.text-justify}\n    :icon-nuxt-nitro{.h-32}\n    :headline[Nitro Engine]\n\n    We worked for 9 months on Nuxt's new server engine for Nuxt: [**Nitro**](/concepts/server-engine). It unlocks new **full-stack capabilities** to Nuxt server and beyond.\n\n    In development, it uses [Rollup](https://rollupjs.org/guide/en/) and [Node.js workers](https://nodejs.org/api/worker_threads.html) for your server code and context isolation. It also **generates your server API** by reading files in [`server/api/`](/docs/directory-structure/server#api-routes) and **server middleware** from [`server/middleware/`](/docs/directory-structure/server#server-middleware).\n\n    In production, it builds your app and server into one universal [`.output`](/docs/directory-structure/output) directory. This **output is light**: minified and removed from any Node.js modules (except polyfills). You can deploy this output on any system supporting JavaScript, from Node.js, Serverless, Workers, Edge-side rendering or purely static.\n\n    The output is combined with both runtime code to run your Nuxt server in any environment (including experimental browser Service Workers!) and serve you static files, making it a **true hybrid framework** for the JAMStack. In addition, a native storage layer is implemented, supporting multi source, drivers and local assets.\n\n    The foundation of the Nitro server is rollup and [h3](https://github.com/unjs/h3): a minimal http framework built for high performance and portability.\n\n    :button-link[Learn more about Nitro]{ href=\"/concepts/server-engine\" size=\"medium\" aria-label=\"Learn more about Nitro\" }\n  ::\n::\n\n::section{.dark:bg-secondary-darkest .bg-gray-50 .py-20 .text-justify}\n  ::nuxt-container{.text-justify}\n    :icon-nuxt-bridge{.h-32}\n    :headline[Nuxt Bridge]\n\n    We moved to [Vue 3](https://v3.vuejs.org/) and re-wrote Nuxt after 4 years of development to make it a strong foundation for the future.\n\n    ### Smooth upgrade to Nuxt 3\n\n    We've worked to make the upgrade as easy as possible between Nuxt 2 and Nuxt 3.\n\n    ::list\n    - Legacy plugins and modules will keep working\n    - Nuxt 2 config is compatible\n    - Partial pages options API available\n    ::\n\n    ### Bringing Nuxt 3 experience to your existing Nuxt 2 project\n\n    As we've been working on new features for Nuxt 3, we've back-ported some of them to Nuxt 2.\n\n    ::list{.mb-8}\n    - Using [Nitro server](/concepts/server-engine) with Nuxt 2\n    - Using Composition API (same as Nuxt 3) with Nuxt 2\n    - Using new CLI and Devtools with Nuxt 2\n    - Progressively upgrade to Nuxt 3\n    - Compatibility with Nuxt 2 module ecosystem\n    - Upgrade piece by piece (Nitro, Composition API, Nuxt Kit)\n    ::\n\n    :button-link[Get started with Nuxt Bridge]{ href=\"/getting-started/bridge\" size=\"medium\" aria-label=\"Get started\" }\n  ::\n::\n","ast":{"type":"root","children":[{"type":"element","tag":"home-hero","props":{":primary":"{\"text\":\"Star on GitHub\",\"url\":\"https://github.com/nuxt/framework\",\"icon\":\"IconGitHub\"}"},"children":[{"type":"element","tag":"template","props":{"v-slot:title":""},"children":[{"type":"element","tag":"prose-paragraph","props":{},"children":[{"type":"text","value":"The Hybrid "},{"type":"element","tag":"span","props":{"className":["text-primary"]},"children":[{"type":"text","value":"Vue"}]},{"type":"text","value":" Framework"}]}],"content":[{"type":"element","tag":"prose-paragraph","props":{},"children":[{"type":"text","value":"The Hybrid "},{"type":"element","tag":"span","props":{"className":["text-primary"]},"children":[{"type":"text","value":"Vue"}]},{"type":"text","value":" Framework"}]}]},{"type":"element","tag":"template","props":{"v-slot:description":""},"children":[{"type":"element","tag":"prose-paragraph","props":{},"children":[{"type":"text","value":"使用 Vue 3 构建您的下一个应用程序，体验混合式渲染、强大的数据获取和新功能。Nuxt 3 是一个开源框架，使 Web 开发变得简单而强大。"}]}],"content":[{"type":"element","tag":"prose-paragraph","props":{},"children":[{"type":"text","value":"使用 Vue 3 构建您的下一个应用程序，体验混合式渲染、强大的数据获取和新功能。Nuxt 3 是一个开源框架，使 Web 开发变得简单而强大。"}]}]},{"type":"element","tag":"template","props":{"v-slot:secondary-button":""},"children":[{"type":"element","tag":"button-link","props":{"ariaLabel":"Get started","href":"/getting-started","size":"medium"},"children":[{"type":"text","value":"开始"}]}],"content":[{"type":"element","tag":"button-link","props":{"ariaLabel":"Get started","href":"/getting-started","size":"medium"},"children":[{"type":"text","value":"开始"}]}]}]},{"type":"text","value":"\n"},{"type":"element","tag":"home-features","props":{"category":"发现","className":["dark:bg-secondary-darkest","bg-gray-50"]},"children":[{"type":"element","tag":"template","props":{"v-slot:title":""},"children":[{"type":"element","tag":"prose-paragraph","props":{},"children":[{"type":"text","value":"新功能"}]}],"content":[{"type":"element","tag":"prose-paragraph","props":{},"children":[{"type":"text","value":"新功能"}]}]},{"type":"element","tag":"template","props":{"v-slot:description":""},"children":[{"type":"element","tag":"prose-paragraph","props":{},"children":[{"type":"text","value":"Nuxt 3 已重新架构，内核更小，并针对更快的性能和更好的开发人员体验进行了优化。"}]}],"content":[{"type":"element","tag":"prose-paragraph","props":{},"children":[{"type":"text","value":"Nuxt 3 已重新架构，内核更小，并针对更快的性能和更好的开发人员体验进行了优化。"}]}]},{"type":"element","tag":"section-content-item","props":{"description":"Up to 75x smaller server deployments and smaller client bundle targeting modern browsers.","image":"IconFeather","imageClass":"w-10 h-10","title":"Lighter"},"children":[]},{"type":"element","tag":"section-content-item","props":{"description":"优化的冷启动与动态服务器代码拆分，由 nitro 提供支持.","image":"IconRabbit","imageClass":"w-10 h-10","title":"Faster"},"children":[]},{"type":"element","tag":"section-content-item","props":{"description":"Incremental Static Generation and other advanced modes are now possible.","image":"IconHybrid","imageClass":"w-10 h-10","title":"Hybrid",":soon":"true"},"children":[]},{"type":"element","tag":"section-content-item","props":{"description":"Fetch data in any component, before or after navigation.","image":"IconSuspense","imageClass":"w-10 h-10","title":"Suspense"},"children":[]},{"type":"element","tag":"section-content-item","props":{"description":"使用 Composition API 和 Nuxt 3 的可组合物实现真正的代码可重用性。","image":"IconCAPI","imageClass":"w-10 h-10","title":"Composition API"},"children":[]},{"type":"element","tag":"section-content-item","props":{"description":"全新的零依赖体验，可轻松搭建脚手架和模块集成。","image":"IconCLI","imageClass":"w-10 h-10","title":"Nuxt CLI"},"children":[]},{"type":"element","tag":"section-content-item","props":{"description":"Work faster with info and quick fixes right in the browser.","image":"IconDevtools","imageClass":"w-10 h-10","title":"Nuxt Devtools",":soon":"true"},"children":[]},{"type":"element","tag":"section-content-item","props":{"description":"Brand new module development with Typescript and cross-version compatibility.","image":"IconKit","imageClass":"w-10 h-10","title":"Nuxt Kit"},"children":[]},{"type":"element","tag":"section-content-item","props":{"description":"Faster build time and smaller bundle size, with no configuration required.","image":"IconWebpack","imageClass":"w-10 h-10","title":"Webpack 5"},"children":[]},{"type":"element","tag":"section-content-item","props":{"description":"Vue 3 是您下一个 Web 应用程序的坚实基础。","image":"IconVite","imageClass":"w-10 h-10","title":"Vite"},"children":[]},{"type":"element","tag":"section-content-item","props":{"description":"Vue 3 is a solid foundation for your next web app.","image":"IconVue","imageClass":"w-10 h-10","title":"Vue 3"},"children":[]},{"type":"element","tag":"section-content-item","props":{"description":"Built with native TypeScript and ESM - no extra steps required.","image":"IconTypeScript","imageClass":"w-10 h-10","title":"TypeScript"},"children":[]},{"type":"element","tag":"template","props":{"v-slot:bottom":""},"children":[{"type":"element","tag":"button-link","props":{"ariaLabel":"Get started","href":"/getting-started","size":"medium"},"children":[{"type":"text","value":"开始"}]}],"content":[{"type":"element","tag":"button-link","props":{"ariaLabel":"Get started","href":"/getting-started","size":"medium"},"children":[{"type":"text","value":"开始"}]}]}]},{"type":"text","value":"\n"},{"type":"element","tag":"section","props":{"className":["py-20","text-lg"]},"children":[{"type":"element","tag":"nuxt-container","props":{"className":["text-justify"]},"children":[{"type":"element","tag":"icon-nuxt-nitro","props":{"className":["h-32"]},"children":[]},{"type":"element","tag":"headline","props":{},"children":[{"type":"text","value":"Nitro Engine"}]},{"type":"element","tag":"prose-paragraph","props":{},"children":[{"type":"text","value":"We worked for 9 months on Nuxt's new server engine for Nuxt: "},{"type":"element","tag":"prose-a","props":{"href":"/concepts/server-engine"},"children":[{"type":"element","tag":"prose-strong","props":{},"children":[{"type":"text","value":"Nitro"}]}]},{"type":"text","value":". It unlocks new "},{"type":"element","tag":"prose-strong","props":{},"children":[{"type":"text","value":"full-stack capabilities"}]},{"type":"text","value":" to Nuxt server and beyond."}]},{"type":"element","tag":"prose-paragraph","props":{},"children":[{"type":"text","value":"In development, it uses "},{"type":"element","tag":"prose-a","props":{"href":"https://rollupjs.org/guide/en/","rel":["nofollow","noopener","noreferrer"],"target":"_blank"},"children":[{"type":"text","value":"Rollup"}]},{"type":"text","value":" and "},{"type":"element","tag":"prose-a","props":{"href":"https://nodejs.org/api/worker_threads.html","rel":["nofollow","noopener","noreferrer"],"target":"_blank"},"children":[{"type":"text","value":"Node.js workers"}]},{"type":"text","value":" for your server code and context isolation. It also "},{"type":"element","tag":"prose-strong","props":{},"children":[{"type":"text","value":"generates your server API"}]},{"type":"text","value":" by reading files in "},{"type":"element","tag":"prose-a","props":{"href":"/docs/directory-structure/server#api-routes"},"children":[{"type":"element","tag":"prose-code-inline","props":{},"children":[{"type":"text","value":"server/api/"}]}]},{"type":"text","value":" and "},{"type":"element","tag":"prose-strong","props":{},"children":[{"type":"text","value":"server middleware"}]},{"type":"text","value":" from "},{"type":"element","tag":"prose-a","props":{"href":"/docs/directory-structure/server#server-middleware"},"children":[{"type":"element","tag":"prose-code-inline","props":{},"children":[{"type":"text","value":"server/middleware/"}]}]},{"type":"text","value":"."}]},{"type":"element","tag":"prose-paragraph","props":{},"children":[{"type":"text","value":"In production, it builds your app and server into one universal "},{"type":"element","tag":"prose-a","props":{"href":"/docs/directory-structure/output"},"children":[{"type":"element","tag":"prose-code-inline","props":{},"children":[{"type":"text","value":".output"}]}]},{"type":"text","value":" directory. This "},{"type":"element","tag":"prose-strong","props":{},"children":[{"type":"text","value":"output is light"}]},{"type":"text","value":": minified and removed from any Node.js modules (except polyfills). You can deploy this output on any system supporting JavaScript, from Node.js, Serverless, Workers, Edge-side rendering or purely static."}]},{"type":"element","tag":"prose-paragraph","props":{},"children":[{"type":"text","value":"The output is combined with both runtime code to run your Nuxt server in any environment (including experimental browser Service Workers!) and serve you static files, making it a "},{"type":"element","tag":"prose-strong","props":{},"children":[{"type":"text","value":"true hybrid framework"}]},{"type":"text","value":" for the JAMStack. In addition, a native storage layer is implemented, supporting multi source, drivers and local assets."}]},{"type":"element","tag":"prose-paragraph","props":{},"children":[{"type":"text","value":"The foundation of the Nitro server is rollup and "},{"type":"element","tag":"prose-a","props":{"href":"https://github.com/unjs/h3","rel":["nofollow","noopener","noreferrer"],"target":"_blank"},"children":[{"type":"text","value":"h3"}]},{"type":"text","value":": a minimal http framework built for high performance and portability."}]},{"type":"element","tag":"button-link","props":{"ariaLabel":"Learn more about Nitro","href":"/concepts/server-engine","size":"medium"},"children":[{"type":"text","value":"Learn more about Nitro"}]}]}]},{"type":"text","value":"\n"},{"type":"element","tag":"section","props":{"className":["dark:bg-secondary-darkest","bg-gray-50","py-20","text-justify"]},"children":[{"type":"element","tag":"nuxt-container","props":{"className":["text-justify"]},"children":[{"type":"element","tag":"icon-nuxt-bridge","props":{"className":["h-32"]},"children":[]},{"type":"element","tag":"headline","props":{},"children":[{"type":"text","value":"Nuxt Bridge"}]},{"type":"element","tag":"prose-paragraph","props":{},"children":[{"type":"text","value":"We moved to "},{"type":"element","tag":"prose-a","props":{"href":"https://v3.vuejs.org/","rel":["nofollow","noopener","noreferrer"],"target":"_blank"},"children":[{"type":"text","value":"Vue 3"}]},{"type":"text","value":" and re-wrote Nuxt after 4 years of development to make it a strong foundation for the future."}]},{"type":"element","tag":"prose-h3","props":{"id":"smooth-upgrade-to-nuxt-3"},"children":[{"type":"element","tag":"prose-a","props":{"href":"#smooth-upgrade-to-nuxt-3"},"children":[{"type":"text","value":"Smooth upgrade to Nuxt 3"}]}]},{"type":"element","tag":"prose-paragraph","props":{},"children":[{"type":"text","value":"We've worked to make the upgrade as easy as possible between Nuxt 2 and Nuxt 3."}]},{"type":"element","tag":"list","props":{},"children":[{"type":"element","tag":"prose-ul","props":{},"children":[{"type":"text","value":"\n"},{"type":"element","tag":"prose-li","props":{},"children":[{"type":"text","value":"\n"},{"type":"text","value":"Legacy plugins and modules will keep working"},{"type":"text","value":"\n"}]},{"type":"text","value":"\n"},{"type":"element","tag":"prose-li","props":{},"children":[{"type":"text","value":"\n"},{"type":"text","value":"Nuxt 2 config is compatible"},{"type":"text","value":"\n"}]},{"type":"text","value":"\n"},{"type":"element","tag":"prose-li","props":{},"children":[{"type":"text","value":"\n"},{"type":"text","value":"Partial pages options API available"},{"type":"text","value":"\n"}]},{"type":"text","value":"\n"}]}]},{"type":"element","tag":"prose-h3","props":{"id":"bringing-nuxt-3-experience-to-your-existing-nuxt-2-project"},"children":[{"type":"element","tag":"prose-a","props":{"href":"#bringing-nuxt-3-experience-to-your-existing-nuxt-2-project"},"children":[{"type":"text","value":"Bringing Nuxt 3 experience to your existing Nuxt 2 project"}]}]},{"type":"element","tag":"prose-paragraph","props":{},"children":[{"type":"text","value":"As we've been working on new features for Nuxt 3, we've back-ported some of them to Nuxt 2."}]},{"type":"element","tag":"list","props":{"className":["mb-8"]},"children":[{"type":"element","tag":"prose-ul","props":{},"children":[{"type":"text","value":"\n"},{"type":"element","tag":"prose-li","props":{},"children":[{"type":"text","value":"\n"},{"type":"text","value":"Using "},{"type":"element","tag":"prose-a","props":{"href":"/concepts/server-engine"},"children":[{"type":"text","value":"Nitro server"}]},{"type":"text","value":" with Nuxt 2"},{"type":"text","value":"\n"}]},{"type":"text","value":"\n"},{"type":"element","tag":"prose-li","props":{},"children":[{"type":"text","value":"\n"},{"type":"text","value":"Using Composition API (same as Nuxt 3) with Nuxt 2"},{"type":"text","value":"\n"}]},{"type":"text","value":"\n"},{"type":"element","tag":"prose-li","props":{},"children":[{"type":"text","value":"\n"},{"type":"text","value":"Using new CLI and Devtools with Nuxt 2"},{"type":"text","value":"\n"}]},{"type":"text","value":"\n"},{"type":"element","tag":"prose-li","props":{},"children":[{"type":"text","value":"\n"},{"type":"text","value":"Progressively upgrade to Nuxt 3"},{"type":"text","value":"\n"}]},{"type":"text","value":"\n"},{"type":"element","tag":"prose-li","props":{},"children":[{"type":"text","value":"\n"},{"type":"text","value":"Compatibility with Nuxt 2 module ecosystem"},{"type":"text","value":"\n"}]},{"type":"text","value":"\n"},{"type":"element","tag":"prose-li","props":{},"children":[{"type":"text","value":"\n"},{"type":"text","value":"Upgrade piece by piece (Nitro, Composition API, Nuxt Kit)"},{"type":"text","value":"\n"}]},{"type":"text","value":"\n"}]}]},{"type":"element","tag":"button-link","props":{"ariaLabel":"Get started","href":"/getting-started/bridge","size":"medium"},"children":[{"type":"text","value":"Get started with Nuxt Bridge"}]}]}]}]},"toc":{"title":"","searchDepth":2,"depth":2,"links":[]}}}